kearas/__init__.py
kearas/pro.py
kearas-0.2.dist-info/METADATA
kearas-0.2.dist-info/WHEEL
kearas-0.2.dist-info/top_level.txt
kearas-0.2.dist-info/RECORD
