Metadata-Version: 2.1
Name: kearas
Version: 0.2
Summary: This is the short description
License: MIT
Requires-Dist: pandas
